FJ_STT/__init__.py
FJ_STT-0.1.dist-info/METADATA
FJ_STT-0.1.dist-info/WHEEL
FJ_STT-0.1.dist-info/top_level.txt
FJ_STT-0.1.dist-info/RECORD
