Metadata-Version: 2.1
Name: FJ-STT
Version: 0.1
Summary: This is speech to text package created by Fardeen Shaikh
Author: Fardeen Shaikh
Author-email: fs5544100@gamil.com
